[
    {
        "name": "Tingting",
        "img_url": "1",
        "evaluate": "Delicious food, excellent service!",
        "star": ""
    },
    {
        "name": "Weihao",
        "img_url": "2",
        "evaluate": "Comfortable environment, rich variety of dishes!",
        "star": ""
    },
    {
        "name": "Daming",
        "img_url": "3",
        "evaluate": "Amazing gastronomic feast!",
        "star": ""
    },
    {
        "name": "Boxiang",
        "img_url": "4",
        "evaluate": "Friendly service, reasonable prices.",
        "star": ""
    },
    {
        "name": "Zhang",
        "img_url": "5",
        "evaluate": "Excellent taste, will come again next time.",
        "star": ""
    },
    {
        "name": "JC",
        "img_url": "6",
        "evaluate": "Unique dishes, impressive.",
        "star": ""
    },
    {
        "name": "Wei",
        "img_url": "7",
        "evaluate": "Super delicious, great value for money.",
        "star": ""
    },
    {
        "name": "Chen",
        "img_url": "8",
        "evaluate": "Warm atmosphere, diverse dishes.",
        "star": ""
    },
    {
        "name": "CF",
        "img_url": "9",
        "evaluate": "Perfect dining experience!",
        "star": ""
    },
    {
        "name": "Zihao",
        "img_url": "10",
        "evaluate": "Fresh food, enthusiastic service.",
        "star": ""
    }
]